CHANGELOG
LICENSE
MANIFEST.in
README
pyilt2report.1
requirements.txt
setup.cfg
setup.py
pyilt2/__init__.py
pyilt2/report.py
pyilt2/version.py
pyilt2.egg-info/PKG-INFO
pyilt2.egg-info/SOURCES.txt
pyilt2.egg-info/dependency_links.txt
pyilt2.egg-info/entry_points.txt
pyilt2.egg-info/requires.txt
pyilt2.egg-info/top_level.txt