Metadata-Version: 1.1
Name: pyilt2
Version: 0.9.4
Summary: A library to access the ILThermo v2.0 database.
Home-page: http://wgserve.de/pyilt2
Author: Frank Roemer
Author-email: froemer76@googlemail.com
License: MIT
Keywords: ILThermo,Ionic Liquids Database
Platform: UNKNOWN
Classifier: Operating System :: OS Independent
Classifier: Development Status :: 4 - Beta
Classifier: License :: OSI Approved :: MIT License
Classifier: Intended Audience :: Science/Research
Classifier: Intended Audience :: Education
Classifier: Intended Audience :: Developers
Classifier: Topic :: Database :: Front-Ends
Classifier: Topic :: Scientific/Engineering :: Chemistry
Classifier: Programming Language :: Python :: 2
Classifier: Programming Language :: Python :: 3
